tlama_core-0.0.3.dist-info/licenses/LICENSE
tlamacore/__init__.py
tlamacore/config/__init__.py
tlamacore/data/__init__.py
tlamacore/data/augmentation.py
tlamacore/data/base_dataloader.py
tlamacore/data/dataloader.py
tlamacore/data/dataset.py
tlamacore/data/preprocessing.py
tlamacore/kernels/__init__.py
tlamacore/models/__init__.py
tlamacore/models/config.py
tlamacore/models/loader.py
tlamacore/models/qwen2.py
tlamacore/models/tlama_base.py
tlamacore/models/utils.py
tlamacore/optim/__init__.py
tlamacore/scripts/__init__.py
tlamacore/tokenizers/__init__.py
tlamacore/training/__init__.py
tlamacore/training/scheduler.py
tlamacore/training/trainer.py
tlamacore/utils/__init__.py
tlamacore/utils/_utils.py
tlama_core-0.0.3.dist-info/METADATA
tlama_core-0.0.3.dist-info/WHEEL
tlama_core-0.0.3.dist-info/top_level.txt
tlama_core-0.0.3.dist-info/RECORD
