Metadata-Version: 2.4
Name: tlama-core
Version: 0.0.3
Summary: Core library for training Tlama models.
Home-page: https://github.com/eigencore/tlama-core
Author: Eigen Core
Author-email: main@eigencore.org
Project-URL: Bug Tracker, https://github.com/eigencore/tlama-core/issues
Project-URL: Documentation, https://eigen-core.gitbook.io/tlama-core-docs
Project-URL: Source Code, https://github.com/eigencore/tlama-core
Keywords: llama,transformers,nlp,machine learning,deep learning
Classifier: Development Status :: 3 - Alpha
Classifier: Intended Audience :: Developers
Classifier: Intended Audience :: Science/Research
Classifier: Topic :: Scientific/Engineering :: Artificial Intelligence
Classifier: Programming Language :: Python :: 3
Classifier: Programming Language :: Python :: 3.8
Classifier: Programming Language :: Python :: 3.9
Classifier: Programming Language :: Python :: 3.10
Classifier: License :: OSI Approved :: Apache Software License
Classifier: Operating System :: OS Independent
Requires-Python: >=3.8
License-File: LICENSE
Requires-Dist: torch>=2.0.0
Requires-Dist: transformers>=4.30.0
Requires-Dist: numpy>=1.20.0
Requires-Dist: einops>=0.6.0
Requires-Dist: flash-attn>=2.0.0
Requires-Dist: xformers>=0.0.20
Requires-Dist: huggingface-hub>=0.16.0
Requires-Dist: tqdm>=4.65.0
Requires-Dist: matplotlib>=3.7.0
Requires-Dist: Pillow>=9.0.0
Requires-Dist: safetensors>=0.3.0
Requires-Dist: triton>=2.0.0
Requires-Dist: rich==13.9.4
Dynamic: author
Dynamic: author-email
Dynamic: classifier
Dynamic: description
Dynamic: description-content-type
Dynamic: home-page
Dynamic: keywords
Dynamic: license-file
Dynamic: project-url
Dynamic: requires-dist
Dynamic: requires-python
Dynamic: summary
